metaflow/R.py
metaflow/__init__.py
metaflow/cards.py
metaflow/cli.py
metaflow/cli_args.py
metaflow/clone_util.py
metaflow/cmd_with_io.py
metaflow/debug.py
metaflow/decorators.py
metaflow/event_logger.py
metaflow/events.py
metaflow/exception.py
metaflow/flowspec.py
metaflow/graph.py
metaflow/includefile.py
metaflow/info_file.py
metaflow/integrations.py
metaflow/lint.py
metaflow/metaflow_config.py
metaflow/metaflow_config_funcs.py
metaflow/metaflow_current.py
metaflow/metaflow_environment.py
metaflow/metaflow_profile.py
metaflow/metaflow_version.py
metaflow/monitor.py
metaflow/multicore_utils.py
metaflow/package.py
metaflow/parameters.py
metaflow/procpoll.py
metaflow/py.typed
metaflow/pylint_wrapper.py
metaflow/runtime.py
metaflow/tagging_util.py
metaflow/task.py
metaflow/tuple_util.py
metaflow/unbounded_foreach.py
metaflow/util.py
metaflow/vendor.py
metaflow/version.py
metaflow/_vendor/__init__.py
metaflow/_vendor/typing_extensions.py
metaflow/_vendor/zipp.py
metaflow/_vendor/click/__init__.py
metaflow/_vendor/click/_bashcomplete.py
metaflow/_vendor/click/_compat.py
metaflow/_vendor/click/_termui_impl.py
metaflow/_vendor/click/_textwrap.py
metaflow/_vendor/click/_unicodefun.py
metaflow/_vendor/click/_winconsole.py
metaflow/_vendor/click/core.py
metaflow/_vendor/click/decorators.py
metaflow/_vendor/click/exceptions.py
metaflow/_vendor/click/formatting.py
metaflow/_vendor/click/globals.py
metaflow/_vendor/click/parser.py
metaflow/_vendor/click/termui.py
metaflow/_vendor/click/testing.py
metaflow/_vendor/click/types.py
metaflow/_vendor/click/utils.py
metaflow/_vendor/importlib_metadata/__init__.py
metaflow/_vendor/importlib_metadata/_adapters.py
metaflow/_vendor/importlib_metadata/_collections.py
metaflow/_vendor/importlib_metadata/_compat.py
metaflow/_vendor/importlib_metadata/_functools.py
metaflow/_vendor/importlib_metadata/_itertools.py
metaflow/_vendor/importlib_metadata/_meta.py
metaflow/_vendor/importlib_metadata/_text.py
metaflow/_vendor/packaging/__init__.py
metaflow_suanpan-0.0.6.dist-info/LICENSE
metaflow_suanpan-0.0.6.dist-info/METADATA
metaflow_suanpan-0.0.6.dist-info/WHEEL
metaflow_suanpan-0.0.6.dist-info/entry_points.txt
metaflow_suanpan-0.0.6.dist-info/top_level.txt
metaflow_suanpan-0.0.6.dist-info/RECORD
