Metadata-Version: 2.1
Name: metaflow-suanpan
Version: 0.0.6
Summary: Metaflow with suanpan plugin, based on metaflow 2.12.22
Author: Metaflow Developers
Author-email: help@metaflow.org
License: Apache Software License
Project-URL: Source, https://github.com/Netflix/metaflow
Project-URL: Issues, https://github.com/Netflix/metaflow/issues
Project-URL: Documentation, https://docs.metaflow.org
Classifier: Development Status :: 5 - Production/Stable
Classifier: License :: OSI Approved :: Apache Software License
Classifier: Operating System :: MacOS :: MacOS X
Classifier: Operating System :: POSIX :: Linux
Classifier: Programming Language :: Python :: 3
Classifier: Programming Language :: Python :: 3.5
Classifier: Programming Language :: Python :: 3.6
Classifier: Programming Language :: Python :: 3.7
Classifier: Programming Language :: Python :: 3.8
Classifier: Programming Language :: Python :: 3.9
Classifier: Programming Language :: Python :: 3.10
Classifier: Programming Language :: Python :: 3.11
Classifier: Programming Language :: Python :: 3.12
License-File: LICENSE
Requires-Dist: requests
Requires-Dist: boto3
Provides-Extra: stubs
Requires-Dist: metaflow-stubs==0.0.6; extra == "stubs"
